{
    "CurveSimulator Documentation": "https://github.com/lichtgestalter/curvesimulator/wiki",
    "Simulation Parameters": {
        "comment": "X048",
        "start_realtime": "06.10.25 15:05:22 [DD.MM.YY hh:mm:ss]",
        "end_realtime": "08.10.25 07:34:40 [DD.MM.YY hh:mm:ss]",
        "run_time": "01:16:29:18 [dd:hh:mm:ss]",
        "run_time_per_iteration": "32.391 [s]",
        "simulations_per_second": "31.614 [iterations*walkers/runtime]",
        "fitting_results_directory": "../results/mcmc/0000/",
        "start_date": 2458400,
        "default_dt": 100000.0,
        "flux_data_points": 146,
        "walkers": 1024,
        "burn_in_steps": 500,
        "steps_after_burn_in": 4000,
        "moves": "(emcee.moves.StretchMove(a=2.0))",
        "thin_samples": 5,
        "tt_file": "../data/TOI-4504/tt.csv",
        "tt_data_points": 17,
        "max_log_prob": -22681.22917286413,
        "max_likelihood_avg_residual_in_std": 51.65636362240278
    },
    "Bodies": {
        "TOI4504": {
            "body_type": "star",
            "primary": "self",
            "radius": 640634640.0,
            "luminosity": 2.3746e+26,
            "limb_darkening_u1": 0.4825125661576079,
            "limb_darkening_u2": 0.20777722805928472,
            "mean_intensity": 0.8045331357961647,
            "intensity": 184170367.64201963,
            "e": -1,
            "i": -19.390607989657003,
            "t": 0.0
        },
        "TOI4504d": {
            "body_type": "planet",
            "primary": "TOI-4504",
            "radius": 72349904.0,
            "luminosity": 0.0,
            "intensity": 0.0,
            "i": 1.5533430342749532,
            "t": 0.0
        },
        "TOI4504c": {
            "body_type": "planet",
            "primary": "TOI-4504",
            "radius": 70755632.4,
            "luminosity": 0.0,
            "intensity": 0.0,
            "i": 1.5671311353657087,
            "Omega": 0.013962634015954637,
            "Omega_deg": 0.8,
            "t": 0.0
        }
    },
    "Fitting Parameters": {
        "TOI4504.mass": {
            "body_index": 0,
            "parameter_name": "mass",
            "unit": "m_jup",
            "long_parameter_name": "mass[m_jup]",
            "scale": 5.268358041405712e-28,
            "startvalue": 932.0,
            "lower": 922.0000000000001,
            "upper": 942.0,
            "sigma": 25.000000000000004,
            "index": 0,
            "body_parameter_name": "TOI4504.mass",
            "long_body_parameter_name": "TOI4504.mass [m_jup]",
            "hdi_min": 928.7548441681686,
            "hdi_max": 935.4543596948739,
            "std": 3.5198329659433965,
            "mean": 931.9965215498088,
            "median": 931.9030983434899,
            "max_likelihood": 931.6833827250915
        },
        "TOI4504d.mass": {
            "body_index": 1,
            "parameter_name": "mass",
            "unit": "m_jup",
            "long_parameter_name": "mass[m_jup]",
            "scale": 5.268358041405712e-28,
            "startvalue": 1.4166,
            "lower": 1.0,
            "upper": 3.0,
            "sigma": 1.5,
            "index": 1,
            "body_parameter_name": "TOI4504d.mass",
            "long_body_parameter_name": "TOI4504d.mass [m_jup]",
            "hdi_min": 1.7330845022587598,
            "hdi_max": 2.9112579783695547,
            "std": 0.5873249888519076,
            "mean": 2.0816689109747553,
            "median": 2.219807754563165,
            "max_likelihood": 2.876912216256897
        },
        "TOI4504d.e": {
            "body_index": 1,
            "parameter_name": "e",
            "unit": "1",
            "long_parameter_name": "e[1]",
            "scale": 1,
            "startvalue": 0.11,
            "lower": 0.1,
            "upper": 0.115,
            "sigma": 0.1,
            "index": 2,
            "body_parameter_name": "TOI4504d.e",
            "long_body_parameter_name": "TOI4504d.e [1]",
            "hdi_min": 0.10573536076497818,
            "hdi_max": 0.11325866583828853,
            "std": 0.003410966403597875,
            "mean": 0.10935535746321627,
            "median": 0.10953711687159148,
            "max_likelihood": 0.11473503072325421
        },
        "TOI4504d.P": {
            "body_index": 1,
            "parameter_name": "P",
            "unit": "d",
            "long_parameter_name": "P[d]",
            "scale": 1.1574074074074073e-05,
            "startvalue": 41.0,
            "lower": 40.6,
            "upper": 41.4,
            "sigma": 0.75,
            "index": 3,
            "body_parameter_name": "TOI4504d.P",
            "long_body_parameter_name": "TOI4504d.P [d]",
            "hdi_min": 41.20143901669435,
            "hdi_max": 41.399999963677224,
            "std": 0.1766458319503273,
            "mean": 41.25211291312325,
            "median": 41.332584820083774,
            "max_likelihood": 41.3999229626296
        },
        "TOI4504d.Omega": {
            "body_index": 1,
            "parameter_name": "Omega",
            "unit": "deg",
            "long_parameter_name": "Omega[deg]",
            "scale": 57.29577951308232,
            "startvalue": 0.0,
            "lower": -1.0,
            "upper": 3.0000000000000004,
            "sigma": 4.0,
            "index": 4,
            "body_parameter_name": "TOI4504d.Omega",
            "long_body_parameter_name": "TOI4504d.Omega [deg]",
            "hdi_min": 0.9157779353333707,
            "hdi_max": 1.8322669195144048,
            "std": 0.47458788222063036,
            "mean": 1.4131829881199771,
            "median": 1.3756025362820634,
            "max_likelihood": 2.3018114467589204
        },
        "TOI4504d.omega": {
            "body_index": 1,
            "parameter_name": "omega",
            "unit": "deg",
            "long_parameter_name": "omega[deg]",
            "scale": 57.29577951308232,
            "startvalue": 105.00000000000001,
            "lower": 90.0,
            "upper": 119.99999999999999,
            "sigma": 119.99999999999999,
            "index": 5,
            "body_parameter_name": "TOI4504d.omega",
            "long_body_parameter_name": "TOI4504d.omega [deg]",
            "hdi_min": 96.10650897337968,
            "hdi_max": 110.36034706258435,
            "std": 7.015213785615818,
            "mean": 103.3103567640293,
            "median": 104.67124819221092,
            "max_likelihood": 108.43192215747578
        },
        "TOI4504d.ma": {
            "body_index": 1,
            "parameter_name": "ma",
            "unit": "deg",
            "long_parameter_name": "ma[deg]",
            "scale": 57.29577951308232,
            "startvalue": -80.0,
            "lower": -180.0,
            "upper": 180.0,
            "sigma": 119.99999999999999,
            "index": 6,
            "body_parameter_name": "TOI4504d.ma",
            "long_body_parameter_name": "TOI4504d.ma [deg]",
            "hdi_min": -76.0279677673229,
            "hdi_max": -44.270103895192875,
            "std": 45.12068657940276,
            "mean": -46.50307469041687,
            "median": -56.14121600180824,
            "max_likelihood": -56.249714912706864
        },
        "TOI4504c.mass": {
            "body_index": 2,
            "parameter_name": "mass",
            "unit": "m_jup",
            "long_parameter_name": "mass[m_jup]",
            "scale": 5.268358041405712e-28,
            "startvalue": 2.7500000000000004,
            "lower": 2.0,
            "upper": 3.5,
            "sigma": 1.5,
            "index": 7,
            "body_parameter_name": "TOI4504c.mass",
            "long_body_parameter_name": "TOI4504c.mass [m_jup]",
            "hdi_min": 2.6478234671131444,
            "hdi_max": 3.1637291145339144,
            "std": 0.2521950416679678,
            "mean": 2.892110139737899,
            "median": 2.893654638188683,
            "max_likelihood": 2.760602235626845
        },
        "TOI4504c.e": {
            "body_index": 2,
            "parameter_name": "e",
            "unit": "1",
            "long_parameter_name": "e[1]",
            "scale": 1,
            "startvalue": 0.07,
            "lower": 0.02,
            "upper": 0.12,
            "sigma": 0.1,
            "index": 8,
            "body_parameter_name": "TOI4504c.e",
            "long_body_parameter_name": "TOI4504c.e [1]",
            "hdi_min": 0.09181915864433458,
            "hdi_max": 0.11620381854029052,
            "std": 0.019422704242220756,
            "mean": 0.09575659112596323,
            "median": 0.10047717588319686,
            "max_likelihood": 0.09231822694734308
        },
        "TOI4504c.P": {
            "body_index": 2,
            "parameter_name": "P",
            "unit": "d",
            "long_parameter_name": "P[d]",
            "scale": 1.1574074074074073e-05,
            "startvalue": 82.7,
            "lower": 82.0,
            "upper": 83.3,
            "sigma": 1.5,
            "index": 9,
            "body_parameter_name": "TOI4504c.P",
            "long_body_parameter_name": "TOI4504c.P [d]",
            "hdi_min": 82.5591042229426,
            "hdi_max": 82.89599581484313,
            "std": 0.18972582800064847,
            "mean": 82.71501843101476,
            "median": 82.68512945123078,
            "max_likelihood": 82.72787269967849
        },
        "TOI4504c.omega": {
            "body_index": 2,
            "parameter_name": "omega",
            "unit": "deg",
            "long_parameter_name": "omega[deg]",
            "scale": 57.29577951308232,
            "startvalue": 271.0,
            "lower": 200.0,
            "upper": 300.0,
            "sigma": 119.99999999999999,
            "index": 10,
            "body_parameter_name": "TOI4504c.omega",
            "long_body_parameter_name": "TOI4504c.omega [deg]",
            "hdi_min": 218.8782151665903,
            "hdi_max": 229.203751906635,
            "std": 11.303878339058999,
            "mean": 227.24680512693106,
            "median": 224.81641514931147,
            "max_likelihood": 219.3701362031397
        },
        "TOI4504c.ma": {
            "body_index": 2,
            "parameter_name": "ma",
            "unit": "deg",
            "long_parameter_name": "ma[deg]",
            "scale": 57.29577951308232,
            "startvalue": 173.0,
            "lower": 0.0,
            "upper": 359.99,
            "sigma": 119.99999999999999,
            "index": 11,
            "body_parameter_name": "TOI4504c.ma",
            "long_body_parameter_name": "TOI4504c.ma [deg]",
            "hdi_min": 211.03943714494685,
            "hdi_max": 226.74301922416544,
            "std": 29.55242466655708,
            "mean": 207.6206303163405,
            "median": 217.51297581686447,
            "max_likelihood": 226.098992283088
        }
    },
    "measured_tt_list": {
        "eclipser": [
            "TOI4504c",
            "TOI4504c",
            "TOI4504c",
            "TOI4504c",
            "TOI4504c",
            "TOI4504c",
            "TOI4504c",
            "TOI4504c",
            "TOI4504c",
            "TOI4504c",
            "TOI4504c",
            "TOI4504c",
            "TOI4504c",
            "TOI4504d",
            "TOI4504d",
            "TOI4504d",
            "TOI4504d"
        ],
        "tt": [
            2458401.4086,
            2458483.211,
            2458565.0902,
            2458647.3328,
            2459065.237,
            2459148.4782,
            2459231.1144,
            2459313.2535,
            2459976.0493,
            2460059.6189,
            2460142.6048,
            2460718.6126,
            2460886.272,
            2460695.5346,
            2460736.6349,
            2460859.2275,
            2460900.06
        ],
        "tt_err": [
            0.02,
            0.02,
            0.02,
            0.02,
            0.006944444,
            0.006944444,
            0.006944444,
            0.006944444,
            0.01,
            0.006944444,
            0.006944444,
            0.006944444,
            0.006944444,
            0.006944444,
            0.006944444,
            0.006944444,
            0.006944444
        ],
        "nearest_sim": [
            2458402.9908368983,
            2458484.059561292,
            2458565.5211796365,
            2458648.0023519862,
            2459065.8262097174,
            2459148.3813083833,
            2459230.6770937312,
            2459312.8046615254,
            2459975.8588330615,
            2460059.747403529,
            2460142.451513807,
            2460718.66589023,
            2460886.224414574,
            2460696.3977605104,
            2460737.0316541856,
            2460859.1645681197,
            2460899.9947432014
        ],
        "delta": [
            1.5822368981316686,
            0.8485612920485437,
            0.4309796364977956,
            0.6695519862696528,
            0.589209717232734,
            -0.09689161647111177,
            -0.4373062686063349,
            -0.44883847469463944,
            -0.19046693854033947,
            0.12850352888926864,
            -0.15328619303181767,
            0.05329022975638509,
            -0.04758542589843273,
            0.8631605105474591,
            0.3967541856691241,
            -0.06293188035488129,
            -0.06525679863989353
        ]
    },
    "ProgramParameters": {
        "config_file": "../configurations/TOI4504/TOI-4504_X048.ini",
        "g": 6.6743e-11,
        "au": 149597870700.0,
        "r_sun": 696342000.0,
        "m_sun": 1.98847e+30,
        "l_sun": 3.83e+26,
        "r_jup": 71492000.0,
        "m_jup": 1.8981246e+27,
        "r_earth": 6378135.0,
        "m_earth": 5.972e+24,
        "v_earth": 29785.2,
        "hour": 3600,
        "day": 86400,
        "year": 31556925.216,
        "rad2deg": 57.29577951308232,
        "verbose": false,
        "transit_precision": 1,
        "dt": 100000.0,
        "video_file": null,
        "flux_file": null,
        "rv_file": null,
        "eclipsers_names": [
            "TOI4504c",
            "TOI4504d"
        ],
        "eclipsees_names": [
            "TOI4504"
        ],
        "result_file": "../results/TOI-4504_debug.json",
        "result_dt": 1000,
        "max_interval_extensions": 5,
        "starts_d": [
            2458400.0
        ],
        "ends_d": [
            2460920.0
        ],
        "dts": [
            1500000.0
        ],
        "starts_s0": [
            0.0
        ],
        "ends_s0": [
            217728000.0
        ],
        "start_indices": [
            0,
            146
        ],
        "max_iterations": [
            146
        ],
        "best_residuals_tt_sum_squared": 1e+99,
        "guifit": false,
        "lmfit": false,
        "lmfit_method": "powell",
        "lmfit_max_tt_delta": 0.0001,
        "flux_weight": 1,
        "tt_weight": 1,
        "target_flux": 0.985,
        "steps": 10000000,
        "chunk_size": 250,
        "bins": [
            200
        ],
        "unit": {
            "mass": "m_jup",
            "radius": "r_jup",
            "e": "1",
            "i": "deg",
            "P": "d",
            "a": "AU",
            "Omega": "deg",
            "omega": "deg",
            "pomega": "deg",
            "L": "deg",
            "ma": "deg",
            "ea": "deg",
            "nu": "deg",
            "T": "s",
            "t": "s"
        },
        "scale": {
            "mass": 5.268358041405712e-28,
            "radius": 1.3987579029821518e-08,
            "e": 1,
            "i": 57.29577951308232,
            "P": 1.1574074074074073e-05,
            "a": 6.684587122268445e-12,
            "Omega": 57.29577951308232,
            "omega": 57.29577951308232,
            "pomega": 57.29577951308232,
            "L": 57.29577951308232,
            "ma": 57.29577951308232,
            "ea": 57.29577951308232,
            "nu": 57.29577951308232,
            "T": 1,
            "t": 1
        }
    }
}